math_time/__init__.py
math_time/date_arithmetic.py
math_time/date_format.py
math_time/timezone.py
math_time-0.1.12.dist-info/LICENSE
math_time-0.1.12.dist-info/METADATA
math_time-0.1.12.dist-info/WHEEL
math_time-0.1.12.dist-info/top_level.txt
math_time-0.1.12.dist-info/RECORD
