Metadata-Version: 2.1
Name: math-time
Version: 0.1.12
Summary: A smal package that help you with time and date conversions and assists with converting between different time zones
Author-email: W3i <hello@mail.w3i.eu>
License: UROPEAN UNION PUBLIC LICENCE v. 1.2
Project-URL: Homepage, https://git.w3i.eu/Kilian/math_time
Project-URL: Bug Tracker, https://git.w3i.eu/Kilian/math_time/issues
Keywords: time,date,datetime,date_time,date-time,date time,timezone,date format,date-format,date_format
Classifier: Programming Language :: Python :: 3
Classifier: Programming Language :: Python :: 3.10
Classifier: Programming Language :: Python :: 3.11
Classifier: Programming Language :: Python :: 3.12
Classifier: Operating System :: OS Independent
Classifier: Development Status :: 2 - Pre-Alpha
Classifier: License :: OSI Approved :: European Union Public Licence 1.2 (EUPL 1.2)
Classifier: Natural Language :: English
Classifier: Topic :: Software Development :: Libraries
Requires-Python: >=3.10
License-File: LICENSE
Requires-Dist: pytz
Requires-Dist: datetime
Requires-Dist: python-dateutil
